{
  "indexes": [
      {
        "collectionGroup": "restaurants",
        "queryScope": "COLLECTION",
        "fields": [
          {
              "fieldPath": "averageRating",
              "order": "ASCENDING"
          },
          {
              "fieldPath": "modificationDate",
              "order": "ASCENDING"
          }
        ]
      },
      {
        "collectionGroup": "restaurants",
        "queryScope": "COLLECTION",
        "fields": [
          {
              "fieldPath": "ownerID",
              "order": "ASCENDING"
          },
          {
              "fieldPath": "modificationDate",
              "order": "ASCENDING"
          }
        ]
      },
      {
        "collectionGroup": "ratings",
        "queryScope": "COLLECTION",
        "fields": [
          {
              "fieldPath": "restaurantID",
              "order": "ASCENDING"
          },
          {
              "fieldPath": "visitDate",
              "order": "DESCENDING"
          }
        ]
      }
  ],
  "fieldOverrides": []
}
